[
  {"iso_a3":"AFG","name":"Afghanistan"},
  {"iso_a3":"ALB","name":"Albania"},
  {"iso_a3":"DZA","name":"Algeria"},
  {"iso_a3":"AND","name":"Andorra"},
  {"iso_a3":"AGO","name":"Angola"},
  {"iso_a3":"ATG","name":"Antigua and Barbuda"},
  {"iso_a3":"ARG","name":"Argentina"},
  {"iso_a3":"ARM","name":"Armenia"},
  {"iso_a3":"AUS","name":"Australia"},
  {"iso_a3":"AUT","name":"Austria"},
  {"iso_a3":"AZE","name":"Azerbaijan"},
  {"iso_a3":"BHS","name":"Bahamas"},
  {"iso_a3":"BHR","name":"Bahrain"},
  {"iso_a3":"BGD","name":"Bangladesh"},
  {"iso_a3":"BRB","name":"Barbados"},
  {"iso_a3":"BLR","name":"Belarus"},
  {"iso_a3":"BEL","name":"Belgium"},
  {"iso_a3":"BLZ","name":"Belize"},
  {"iso_a3":"BEN","name":"Benin"},
  {"iso_a3":"BTN","name":"Bhutan"},
  {"iso_a3":"BOL","name":"Bolivia"},
  {"iso_a3":"BIH","name":"Bosnia and Herzegovina"},
  {"iso_a3":"BWA","name":"Botswana"},
  {"iso_a3":"BRA","name":"Brazil"},
  {"iso_a3":"BRN","name":"Brunei"},
  {"iso_a3":"BGR","name":"Bulgaria"},
  {"iso_a3":"BFA","name":"Burkina Faso"},
  {"iso_a3":"BDI","name":"Burundi"},
  {"iso_a3":"KHM","name":"Cambodia"},
  {"iso_a3":"CMR","name":"Cameroon"},
  {"iso_a3":"CAN","name":"Canada"},
  {"iso_a3":"CPV","name":"Cape Verde"},
  {"iso_a3":"CAF","name":"Central African Republic"},
  {"iso_a3":"TCD","name":"Chad"},
  {"iso_a3":"CHL","name":"Chile"},
  {"iso_a3":"CHN","name":"China"},
  {"iso_a3":"COL","name":"Colombia"},
  {"iso_a3":"COM","name":"Comoros"},
  {"iso_a3":"COG","name":"Congo"},
  {"iso_a3":"COD","name":"Congo (Democratic Republic)"},
  {"iso_a3":"CRI","name":"Costa Rica"},
  {"iso_a3":"CIV","name":"Côte d'Ivoire"},
  {"iso_a3":"HRV","name":"Croatia"},
  {"iso_a3":"CUB","name":"Cuba"},
  {"iso_a3":"CYP","name":"Cyprus"},
  {"iso_a3":"CZE","name":"Czechia"},
  {"iso_a3":"DNK","name":"Denmark"},
  {"iso_a3":"DJI","name":"Djibouti"},
  {"iso_a3":"DMA","name":"Dominica"},
  {"iso_a3":"DOM","name":"Dominican Republic"},
  {"iso_a3":"ECU","name":"Ecuador"},
  {"iso_a3":"EGY","name":"Egypt"},
  {"iso_a3":"SLV","name":"El Salvador"},
  {"iso_a3":"GNQ","name":"Equatorial Guinea"},
  {"iso_a3":"ERI","name":"Eritrea"},
  {"iso_a3":"EST","name":"Estonia"},
  {"iso_a3":"SWZ","name":"Eswatini"},
  {"iso_a3":"ETH","name":"Ethiopia"},
  {"iso_a3":"FJI","name":"Fiji"},
  {"iso_a3":"FIN","name":"Finland"},
  {"iso_a3":"FRA","name":"France"},
  {"iso_a3":"GAB","name":"Gabon"},
  {"iso_a3":"GMB","name":"Gambia"},
  {"iso_a3":"GEO","name":"Georgia"},
  {"iso_a3":"DEU","name":"Germany"},
  {"iso_a3":"GHA","name":"Ghana"},
  {"iso_a3":"GRC","name":"Greece"},
  {"iso_a3":"GRD","name":"Grenada"},
  {"iso_a3":"GTM","name":"Guatemala"},
  {"iso_a3":"GIN","name":"Guinea"},
  {"iso_a3":"GNB","name":"Guinea-Bissau"},
  {"iso_a3":"GUY","name":"Guyana"},
  {"iso_a3":"HTI","name":"Haiti"},
  {"iso_a3":"HND","name":"Honduras"},
  {"iso_a3":"HUN","name":"Hungary"},
  {"iso_a3":"ISL","name":"Iceland"},
  {"iso_a3":"IND","name":"India"},
  {"iso_a3":"IDN","name":"Indonesia"},
  {"iso_a3":"IRN","name":"Iran"},
  {"iso_a3":"IRQ","name":"Iraq"},
  {"iso_a3":"IRL","name":"Ireland"},
  {"iso_a3":"ISR","name":"Israel"},
  {"iso_a3":"ITA","name":"Italy"},
  {"iso_a3":"JAM","name":"Jamaica"},
  {"iso_a3":"JPN","name":"Japan"},
  {"iso_a3":"JOR","name":"Jordan"},
  {"iso_a3":"KAZ","name":"Kazakhstan"},
  {"iso_a3":"KEN","name":"Kenya"},
  {"iso_a3":"KIR","name":"Kiribati"},
  {"iso_a3":"PRK","name":"Korea (North)"},
  {"iso_a3":"KOR","name":"Korea (South)"},
  {"iso_a3":"KWT","name":"Kuwait"},
  {"iso_a3":"KGZ","name":"Kyrgyzstan"},
  {"iso_a3":"LAO","name":"Laos"},
  {"iso_a3":"LVA","name":"Latvia"},
  {"iso_a3":"LBN","name":"Lebanon"},
  {"iso_a3":"LSO","name":"Lesotho"},
  {"iso_a3":"LBR","name":"Liberia"},
  {"iso_a3":"LBY","name":"Libya"},
  {"iso_a3":"LIE","name":"Liechtenstein"},
  {"iso_a3":"LTU","name":"Lithuania"},
  {"iso_a3":"LUX","name":"Luxembourg"},
  {"iso_a3":"MDG","name":"Madagascar"},
  {"iso_a3":"MWI","name":"Malawi"},
  {"iso_a3":"MYS","name":"Malaysia"},
  {"iso_a3":"MDV","name":"Maldives"},
  {"iso_a3":"MLI","name":"Mali"},
  {"iso_a3":"MLT","name":"Malta"},
  {"iso_a3":"MHL","name":"Marshall Islands"},
  {"iso_a3":"MRT","name":"Mauritania"},
  {"iso_a3":"MUS","name":"Mauritius"},
  {"iso_a3":"MEX","name":"Mexico"},
  {"iso_a3":"FSM","name":"Micronesia"},
  {"iso_a3":"MDA","name":"Moldova"},
  {"iso_a3":"MCO","name":"Monaco"},
  {"iso_a3":"MNG","name":"Mongolia"},
  {"iso_a3":"MNE","name":"Montenegro"},
  {"iso_a3":"MAR","name":"Morocco"},
  {"iso_a3":"MOZ","name":"Mozambique"},
  {"iso_a3":"MMR","name":"Myanmar"},
  {"iso_a3":"NAM","name":"Namibia"},
  {"iso_a3":"NRU","name":"Nauru"},
  {"iso_a3":"NPL","name":"Nepal"},
  {"iso_a3":"NLD","name":"Netherlands"},
  {"iso_a3":"NZL","name":"New Zealand"},
  {"iso_a3":"NIC","name":"Nicaragua"},
  {"iso_a3":"NER","name":"Niger"},
  {"iso_a3":"NGA","name":"Nigeria"},
  {"iso_a3":"MKD","name":"North Macedonia"},
  {"iso_a3":"NOR","name":"Norway"},
  {"iso_a3":"OMN","name":"Oman"},
  {"iso_a3":"PAK","name":"Pakistan"},
  {"iso_a3":"PLW","name":"Palau"},
  {"iso_a3":"PAN","name":"Panama"},
  {"iso_a3":"PNG","name":"Papua New Guinea"},
  {"iso_a3":"PRY","name":"Paraguay"},
  {"iso_a3":"PER","name":"Peru"},
  {"iso_a3":"PHL","name":"Philippines"},
  {"iso_a3":"POL","name":"Poland"},
  {"iso_a3":"PRT","name":"Portugal"},
  {"iso_a3":"QAT","name":"Qatar"},
  {"iso_a3":"ROU","name":"Romania"},
  {"iso_a3":"RUS","name":"Russia"},
  {"iso_a3":"RWA","name":"Rwanda"},
  {"iso_a3":"KNA","name":"Saint Kitts and Nevis"},
  {"iso_a3":"LCA","name":"Saint Lucia"},
  {"iso_a3":"VCT","name":"Saint Vincent and the Grenadines"},
  {"iso_a3":"WSM","name":"Samoa"},
  {"iso_a3":"SMR","name":"San Marino"},
  {"iso_a3":"STP","name":"Sao Tome and Principe"},
  {"iso_a3":"SAU","name":"Saudi Arabia"},
  {"iso_a3":"SEN","name":"Senegal"},
  {"iso_a3":"SRB","name":"Serbia"},
  {"iso_a3":"SYC","name":"Seychelles"},
  {"iso_a3":"SLE","name":"Sierra Leone"},
  {"iso_a3":"SGP","name":"Singapore"},
  {"iso_a3":"SVK","name":"Slovakia"},
  {"iso_a3":"SVN","name":"Slovenia"},
  {"iso_a3":"SLB","name":"Solomon Islands"},
  {"iso_a3":"SOM","name":"Somalia"},
  {"iso_a3":"ZAF","name":"South Africa"},
  {"iso_a3":"SSD","name":"South Sudan"},
  {"iso_a3":"ESP","name":"Spain"},
  {"iso_a3":"LKA","name":"Sri Lanka"},
  {"iso_a3":"SDN","name":"Sudan"},
  {"iso_a3":"SUR","name":"Suriname"},
  {"iso_a3":"SWE","name":"Sweden"},
  {"iso_a3":"CHE","name":"Switzerland"},
  {"iso_a3":"SYR","name":"Syria"},
  {"iso_a3":"TWN","name":"Taiwan"},
  {"iso_a3":"TJK","name":"Tajikistan"},
  {"iso_a3":"TZA","name":"Tanzania"},
  {"iso_a3":"THA","name":"Thailand"},
  {"iso_a3":"TLS","name":"Timor-Leste"},
  {"iso_a3":"TGO","name":"Togo"},
  {"iso_a3":"TON","name":"Tonga"},
  {"iso_a3":"TTO","name":"Trinidad and Tobago"},
  {"iso_a3":"TUN","name":"Tunisia"},
  {"iso_a3":"TUR","name":"Turkey"},
  {"iso_a3":"TKM","name":"Turkmenistan"},
  {"iso_a3":"TUV","name":"Tuvalu"},
  {"iso_a3":"UGA","name":"Uganda"},
  {"iso_a3":"UKR","name":"Ukraine"},
  {"iso_a3":"ARE","name":"United Arab Emirates"},
  {"iso_a3":"GBR","name":"United Kingdom"},
  {"iso_a3":"USA","name":"United States"},
  {"iso_a3":"URY","name":"Uruguay"},
  {"iso_a3":"UZB","name":"Uzbekistan"},
  {"iso_a3":"VUT","name":"Vanuatu"},
  {"iso_a3":"VAT","name":"Vatican City"},
  {"iso_a3":"VEN","name":"Venezuela"},
  {"iso_a3":"VNM","name":"Vietnam"},
  {"iso_a3":"YEM","name":"Yemen"},
  {"iso_a3":"ZMB","name":"Zambia"},
  {"iso_a3":"ZWE","name":"Zimbabwe"}
]